setup.py
duybhsoft_train_custom/__init__.py
duybhsoft_train_custom/process_data.py
duybhsoft_train_custom/train.py
duybhsoft_train_custom/train_model.py
duybhsoft_train_custom/train_model_argparam.py
duybhsoft_train_custom/utils.py
duybhsoft_train_custom.egg-info/PKG-INFO
duybhsoft_train_custom.egg-info/SOURCES.txt
duybhsoft_train_custom.egg-info/dependency_links.txt
duybhsoft_train_custom.egg-info/requires.txt
duybhsoft_train_custom.egg-info/top_level.txt